{
  "closed_solved_skipped": [
    "arc2:0934a4d8",
    "arc2:135a2760",
    "arc2:136b0064",
    "arc2:13e47133",
    "arc2:142ca369",
    "arc2:16b78196",
    "arc2:16de56c4",
    "arc2:1818057f",
    "arc2:195c6913",
    "arc2:1ae2feb7",
    "arc2:20270e3b",
    "arc2:20a9e565",
    "arc2:21897d95",
    "arc2:221dfab4",
    "arc2:247ef758",
    "arc2:269e22fb",
    "arc2:271d71e2",
    "arc2:28a6681f",
    "arc2:291dc1e1",
    "arc2:2b83f449",
    "arc2:2ba387bc",
    "arc2:2c181942",
    "arc2:2d0172a1",
    "arc2:31f7f899",
    "arc2:332f06d7",
    "arc2:35ab12c3",
    "arc2:36a08778",
    "arc2:38007db0",
    "arc2:3a25b0d8",
    "arc2:3dc255db",
    "arc2:3e6067c3",
    "arc2:409aa875",
    "arc2:446ef5d2",
    "arc2:45a5af55",
    "arc2:4a21e3da",
    "arc2:4c3d4a41",
    "arc2:4c416de3",
    "arc2:4c7dc4dd",
    "arc2:4e34c42c",
    "arc2:53fb4810",
    "arc2:5545f144",
    "arc2:581f7754",
    "arc2:58490d8a",
    "arc2:58f5dbd5",
    "arc2:5961cc34",
    "arc2:5dbc8537",
    "arc2:62593bfd",
    "arc2:64efde09",
    "arc2:65b59efc",
    "arc2:67e490f4",
    "arc2:6e453dd6",
    "arc2:6e4f6532",
    "arc2:6ffbe589",
    "arc2:71e489b6",
    "arc2:7491f3cf",
    "arc2:7666fa5d",
    "arc2:78332cb0",
    "arc2:7b0280bc",
    "arc2:7b3084d4",
    "arc2:7b5033c1",
    "arc2:7b80bb43",
    "arc2:7c66cb00",
    "arc2:7ed72f31",
    "arc2:800d221b",
    "arc2:80a900e0",
    "arc2:8698868d",
    "arc2:88bcf3b4",
    "arc2:88e364bc",
    "arc2:89565ca0",
    "arc2:898e7135",
    "arc2:8b7bacbf",
    "arc2:8b9c3697",
    "arc2:8e5c0c38",
    "arc2:8f215267",
    "arc2:8f3a5a89",
    "arc2:9385bd28",
    "arc2:97d7923e",
    "arc2:981571dc",
    "arc2:9aaea919",
    "arc2:9bbf930d",
    "arc2:a251c730",
    "arc2:a25697e4",
    "arc2:a32d8b75",
    "arc2:a395ee82",
    "arc2:a47bf94d",
    "arc2:a6f40cea",
    "arc2:aa4ec2a5",
    "arc2:abc82100",
    "arc2:b0039139",
    "arc2:b10624e5",
    "arc2:b5ca7ac4",
    "arc2:b6f77b65",
    "arc2:b99e7126",
    "arc2:b9e38dc0",
    "arc2:bf45cf4b",
    "arc2:c4d067a0",
    "arc2:c7f57c3e",
    "arc2:cb2d8a2c",
    "arc2:cbebaa4b",
    "arc2:d35bdbdc",
    "arc2:d59b0160",
    "arc2:d8e07eb2",
    "arc2:da515329",
    "arc2:db0c5428",
    "arc2:db695cfb",
    "arc2:dbff022c",
    "arc2:dd6b8c4b",
    "arc2:de809cff",
    "arc2:dfadab01",
    "arc2:e12f9a14",
    "arc2:e3721c99",
    "arc2:e376de54",
    "arc2:e8686506",
    "arc2:e87109e9",
    "arc2:edb79dae",
    "arc2:eee78d87",
    "arc2:f560132c",
    "arc2:f931b4a8",
    "arc2:faa9f03d",
    "arc2:fc7cae8d"
  ],
  "next_apply_loop": [],
  "peer_in_flight": [
    {
      "agent": "cursor-sync",
      "tasks": [
        "faa9f03d"
      ],
      "goal": "close last open to 172/172"
    }
  ],
  "note": "CLOSED faa9f03d (+2 => 172/172). ARC-AGI-2 labeled eval COMPLETE. No Kaggle.",
  "recorded_at_utc": "2026-07-21T17:01:39Z"
}
