{
  "task_id": "d59b0160",
  "exam": "ARC-AGI-2",
  "language_game_class": "S3_PUB_EXACT",
  "status": "CLOSED",
  "last_gate": "LOCKED",
  "train": 3,
  "test": 1,
  "engine": "s3_g_d59b0160",
  "observations": [
    "Public train-exact FoT engine s3_g_d59b0160",
    "Train 3/3 labeled eval 1/1"
  ],
  "validator": "demonstration_replay+labeled_eval",
  "validator_result": {
    "accepted": true,
    "detail": "train_replay_3_3_eval_1_1",
    "train_replay": "3/3",
    "labeled_eval": "1/1"
  },
  "mastery_eval": "163/172",
  "mastery_train": "298/1076",
  "recorded_at_utc": "2026-07-21T16:44:10Z",
  "kaggle_submit": false
}
