{
  "licensed": "170/259",
  "licensed_pct": 65.64,
  "identity": 89,
  "submission_sha256": "6a3de66c75f7d0375c80a710e7d9823508b6ded57fa5f325f6010da41449db2c",
  "new_closes_this_turn": [
    "137eaa0f",
    "18286ef8",
    "1990f7a8",
    "2bcee788",
    "32597951",
    "3bdb4ada"
  ],
  "new_licensed_grids_this_turn": 6,
  "commit_base": "f1f47a5",
  "target": 200,
  "no_submit": true,
  "hle_left_alive": true,
  "exp_left_alive": true,
  "recorded_at_utc": "2026-07-22T04:42:56.213304+00:00"
}
